{"name": "4", "children": [{"name": "1", "children": [{"url": "http://static.flickr.com/8203/8287735042_06aafe8583_z.jpg", "name": "", "size": 1}]}, {"name": "0", "children": [{"url": "http://static.flickr.com/7003/6658393789_67ea960013_z.jpg", "name": "", "size": 1}, {"url": "http://static.flickr.com/2104/2477176431_a6d1d0da19_z.jpg", "name": "", "size": 1}, {"url": "http://static.flickr.com/3123/3144704880_7b0bd9d995_z.jpg", "name": "", "size": 1}, {"url": "http://static.flickr.com/2535/3865629214_c691b8bb08_z.jpg", "name": "", "size": 1}, {"url": "http://static.flickr.com/2817/9191966342_6f4b5b3be8_z.jpg", "name": "", "size": 1}, {"url": "http://static.flickr.com/36/118200650_094a71d796_z.jpg", "name": "", "size": 1}, {"url": "http://static.flickr.com/1220/3170802894_d646cfccf8_z.jpg", "name": "", "size": 1}, {"url": "http://static.flickr.com/7225/7172294050_4b3e083e53_z.jpg", "name": "", "size": 1}, {"url": "http://static.flickr.com/6149/6012208602_c8f8d00547_z.jpg", "name": "", "size": 1}, {"url": "http://static.flickr.com/5059/5585544327_05e247e5be_z.jpg", "name": "", "size": 1}, {"url": "http://static.flickr.com/26/88045918_eeebda131d_z.jpg", "name": "", "size": 1}, {"url": "http://static.flickr.com/8097/8421159515_88bb53064f_z.jpg", "name": "", "size": 1}, {"url": "http://static.flickr.com/2173/1761206085_02fbfaef72_z.jpg", "name": "", "size": 1}, {"url": "http://static.flickr.com/3579/3424330525_e164a02fd8_z.jpg", "name": "", "size": 1}, {"url": "http://static.flickr.com/3577/3311329387_8965be03d5_z.jpg", "name": "", "size": 1}, {"url": "http://static.flickr.com/2323/2264549917_36f4e5d65a_z.jpg", "name": "", "size": 1}, {"url": "http://static.flickr.com/209/503388951_06eb3b85e0_z.jpg", "name": "", "size": 1}, {"url": "http://static.flickr.com/2577/3814758915_cb0616a04d_z.jpg", "name": "", "size": 1}, {"url": "http://static.flickr.com/6109/6340041782_6ea1d98f87_z.jpg", "name": "", "size": 1}, {"url": "http://static.flickr.com/5282/5350763244_b73d8ee331_z.jpg", "name": "", "size": 1}, {"url": "http://static.flickr.com/4126/5089139433_e3393d92fd_z.jpg", "name": "", "size": 1}, {"url": "http://static.flickr.com/141/328073574_6e93292844_z.jpg", "name": "", "size": 1}, {"url": "http://static.flickr.com/2387/2460400865_1f522c6a5c_z.jpg", "name": "", "size": 1}, {"url": "http://static.flickr.com/1292/1363495937_0e0df4e095_z.jpg", "name": "", "size": 1}, {"url": "http://static.flickr.com/3486/4082304951_0817a4f620_z.jpg", "name": "", "size": 1}, {"url": "http://static.flickr.com/146/434607774_16d3edeeda_z.jpg", "name": "", "size": 1}, {"url": "http://static.flickr.com/28/46358484_40b8e2bec3_z.jpg", "name": "", "size": 1}, {"url": "http://static.flickr.com/8158/7580579588_c82521442a_z.jpg", "name": "", "size": 1}, {"url": "http://static.flickr.com/36/84845021_312dc211bd_z.jpg", "name": "", "size": 1}, {"url": "http://static.flickr.com/3125/2437801690_e8e597a9f5_z.jpg", "name": "", "size": 1}, {"url": "http://static.flickr.com/2219/2058778526_7745140b2a_z.jpg", "name": "", "size": 1}, {"url": "http://static.flickr.com/6087/6148272744_c64c88e827_z.jpg", "name": "", "size": 1}, {"url": "http://static.flickr.com/173/448955591_6af238d1d8_z.jpg", "name": "", "size": 1}, {"url": "http://static.flickr.com/6069/6127282688_0cd5b29fc1_z.jpg", "name": "", "size": 1}, {"url": "http://static.flickr.com/5201/5229288189_3d94f19605_z.jpg", "name": "", "size": 1}, {"url": "http://static.flickr.com/38/84755737_c628131dff_z.jpg", "name": "", "size": 1}, {"url": "http://static.flickr.com/3605/3414320314_a9e0058519_z.jpg", "name": "", "size": 1}, {"url": "http://static.flickr.com/2432/4022255913_145492c378_z.jpg", "name": "", "size": 1}, {"url": "http://static.flickr.com/2637/4035842467_727276b8c9_z.jpg", "name": "", "size": 1}, {"url": "http://static.flickr.com/2125/2857050843_2139976c98_z.jpg", "name": "", "size": 1}, {"url": "http://static.flickr.com/4084/5216136284_139987ce72_z.jpg", "name": "", "size": 1}, {"url": "http://static.flickr.com/2544/5849144961_6b2b96a559_z.jpg", "name": "", "size": 1}, {"url": "http://static.flickr.com/4047/4173161893_b5431721f7_z.jpg", "name": "", "size": 1}, {"url": "http://static.flickr.com/7144/6603006227_0b84cdd6ac_z.jpg", "name": "", "size": 1}, {"url": "http://static.flickr.com/49/191371569_6c23204ea4_z.jpg", "name": "", "size": 1}, {"url": "http://static.flickr.com/8371/8463573478_a97c96d82f_z.jpg", "name": "", "size": 1}, {"url": "http://static.flickr.com/2067/2113627890_e543d11d7a_z.jpg", "name": "", "size": 1}, {"url": "http://static.flickr.com/254/446997092_6f93325d98_z.jpg", "name": "", "size": 1}, {"url": "http://static.flickr.com/2692/4460193230_72542a351f_z.jpg", "name": "", "size": 1}, {"url": "http://static.flickr.com/20/70361354_9dcf18f882_z.jpg", "name": "", "size": 1}, {"url": "http://static.flickr.com/17/22016838_703efe098f_z.jpg", "name": "", "size": 1}, {"url": "http://static.flickr.com/8031/7996140357_60c0089dd0_z.jpg", "name": "", "size": 1}, {"url": "http://static.flickr.com/2285/5791453092_ba14ec5148_z.jpg", "name": "", "size": 1}, {"url": "http://static.flickr.com/147/370603295_503b670293_z.jpg", "name": "", "size": 1}, {"url": "http://static.flickr.com/8089/8554065103_8fe6f0aa83_z.jpg", "name": "", "size": 1}, {"url": "http://static.flickr.com/3019/2979821307_a9e1fe5d4e_z.jpg", "name": "", "size": 1}, {"url": "http://static.flickr.com/1417/1275095174_b10f717ff8_z.jpg", "name": "", "size": 1}, {"url": "http://static.flickr.com/5018/5524325976_8e43e627be_z.jpg", "name": "", "size": 1}, {"url": "http://static.flickr.com/4043/4427023732_077f6ae824_z.jpg", "name": "", "size": 1}, {"url": "http://static.flickr.com/1196/1438503793_478f74a230_z.jpg", "name": "", "size": 1}, {"url": "http://static.flickr.com/2191/1506165378_8fea7ef29f_z.jpg", "name": "", "size": 1}, {"url": "http://static.flickr.com/5211/5537050637_a8c86316f1_z.jpg", "name": "", "size": 1}, {"url": "http://static.flickr.com/93/236237634_509453f7d0_z.jpg", "name": "", "size": 1}, {"url": "http://static.flickr.com/136/348023281_06f7e6e183_z.jpg", "name": "", "size": 1}, {"url": "http://static.flickr.com/3547/3341082136_3aec1d4453_z.jpg", "name": "", "size": 1}, {"url": "http://static.flickr.com/3538/3352592822_d37f6bc818_z.jpg", "name": "", "size": 1}, {"url": "http://static.flickr.com/5122/5276813857_a177c20cc6_z.jpg", "name": "", "size": 1}, {"url": "http://static.flickr.com/2181/2411966151_8a0b1b09ec_z.jpg", "name": "", "size": 1}]}, {"name": "3", "children": [{"url": "http://static.flickr.com/5261/5585356398_3fdf68c802_z.jpg", "name": "", "size": 1}, {"url": "http://static.flickr.com/4070/4519729092_e740d31b80_z.jpg", "name": "", "size": 1}, {"url": "http://static.flickr.com/2481/3577774541_3f549d6ac0_z.jpg", "name": "", "size": 1}, {"url": "http://static.flickr.com/2021/1528837672_3b430e8009_z.jpg", "name": "", "size": 1}, {"url": "http://static.flickr.com/203/499246110_76df0c759c_z.jpg", "name": "", "size": 1}, {"url": "http://static.flickr.com/3044/2299090139_384a8edcc2_z.jpg", "name": "", "size": 1}, {"url": "http://static.flickr.com/2130/2540382175_018275b937_z.jpg", "name": "", "size": 1}, {"url": "http://static.flickr.com/187/447292062_f1d2c919d6_z.jpg", "name": "", "size": 1}, {"url": "http://static.flickr.com/2104/2477176431_a6d1d0da19_z.jpg", "name": "", "size": 1}, {"url": "http://static.flickr.com/3132/2370197830_8a585a9b60_z.jpg", "name": "", "size": 1}, {"url": "http://static.flickr.com/3352/3437908105_7f679715ce_z.jpg", "name": "", "size": 1}, {"url": "http://static.flickr.com/3583/3472081950_70aaea19ac_z.jpg", "name": "", "size": 1}, {"url": "http://static.flickr.com/2775/4519689430_3ec5f7194d_z.jpg", "name": "", "size": 1}, {"url": "http://static.flickr.com/2173/1761206085_02fbfaef72_z.jpg", "name": "", "size": 1}, {"url": "http://static.flickr.com/3498/3754973571_563e117828_z.jpg", "name": "", "size": 1}, {"url": "http://static.flickr.com/5290/5235947740_1f42b6fe54_z.jpg", "name": "", "size": 1}, {"url": "http://static.flickr.com/1235/1474782128_659c5d6e10_z.jpg", "name": "", "size": 1}, {"url": "http://static.flickr.com/7082/7375137778_ec53b6fd1e_z.jpg", "name": "", "size": 1}, {"url": "http://static.flickr.com/6025/5900880620_88b4bd17af_z.jpg", "name": "", "size": 1}, {"url": "http://static.flickr.com/7180/6866454035_87012e2b92_z.jpg", "name": "", "size": 1}, {"url": "http://static.flickr.com/2224/2308040897_bb6fd19c6f_z.jpg", "name": "", "size": 1}, {"url": "http://static.flickr.com/6109/6340041782_6ea1d98f87_z.jpg", "name": "", "size": 1}, {"url": "http://static.flickr.com/3352/3196361007_87cd97c146_z.jpg", "name": "", "size": 1}]}, {"name": "2", "children": [{"url": "http://static.flickr.com/26/35367584_738f5d0863_z.jpg", "name": "", "size": 1}, {"url": "http://static.flickr.com/3443/3736990649_d12370cf06_z.jpg", "name": "", "size": 1}, {"url": "http://static.flickr.com/3024/3025809710_264f8bb294_z.jpg", "name": "", "size": 1}, {"url": "http://static.flickr.com/3788/11014201903_d6c5fda1af_z.jpg", "name": "", "size": 1}, {"url": "http://static.flickr.com/16/21681821_05ad3fdcce_z.jpg", "name": "", "size": 1}, {"url": "http://static.flickr.com/5216/5416620929_181e42100f_z.jpg", "name": "", "size": 1}]}]}